README.md
setup.py
lockadb/__init__.py
lockadb/client.py
lockadb/config.py
lockadb/server.py
lockadb.egg-info/PKG-INFO
lockadb.egg-info/SOURCES.txt
lockadb.egg-info/dependency_links.txt
lockadb.egg-info/entry_points.txt
lockadb.egg-info/requires.txt
lockadb.egg-info/top_level.txt