Metadata-Version: 1.0
Name: lockadb
Version: 0.1.0
Summary: lockable android debug bridge, for managing devices precisely and safely
Home-page: https://github.com/williamfzc/lockadb
Author: williamfzc
Author-email: fengzc@vip.qq.com
License: UNKNOWN
Platform: UNKNOWN
